Metadata-Version: 2.1
Name: modular_time_fuzzer
Version: 0.0.7
Summary: modular time fuzzer
Author-email: gogo246475 <gogo246475@gmail.com>
Project-URL: Homepage, https://github.com/gogo2464/modular-time-fuzzer/
Project-URL: Issues, https://github.com/gogo2464/modular-time-fuzzer/issues/
Classifier: Programming Language :: Python :: 3
Classifier: Operating System :: OS Independent
Requires-Python: >=3.8
Requires-Dist: requests
Requires-Dist: argparse
